multi_date_picker/MultiDatePicker.py
multi_date_picker/__init__.py
multi_date_picker/_imports_.py
multi_date_picker/metadata.json
multi_date_picker/multi_date_picker.min.js
multi_date_picker/multi_date_picker.min.js.map
multi_date_picker/package-info.json
multi_date_picker-0.0.2.dist-info/LICENSE
multi_date_picker-0.0.2.dist-info/METADATA
multi_date_picker-0.0.2.dist-info/WHEEL
multi_date_picker-0.0.2.dist-info/top_level.txt
multi_date_picker-0.0.2.dist-info/RECORD
