Metadata-Version: 2.1
Name: multi-date-picker
Version: 0.0.2
Summary: Project Description
Author: Fevry Remy <fevryremy@gmail.com>
License: MIT
Classifier: Framework :: Dash
License-File: LICENSE
